demos/__init__.py
demos/pytorch_wArgs_demo.py
demos/wArgsCall_lazy_demo.py
demos/wArgsClass_lazy_demo.py
demos/wildArgs_eager_demo.py
demos/wildArgs_lazy_demo.py
wArgs/__init__.py
wArgs/core.py
wArgs/tools.py
wArgs/tests/__init__.py
wArgs/tests/test_call.py
wArgs/tests/test_class.py
wArgs/tests/test_wild.py
wArgsTools-0.1.0.dist-info/LICENSE
wArgsTools-0.1.0.dist-info/METADATA
wArgsTools-0.1.0.dist-info/WHEEL
wArgsTools-0.1.0.dist-info/top_level.txt
wArgsTools-0.1.0.dist-info/RECORD
