Metadata-Version: 2.1
Name: wArgsTools
Version: 0.1.0
Summary: A wrapping tool to inspect and exports callable args into an argparse parser
Home-page: https://www.deakin.edu.au/about-deakin/people/mohammed-hossny
Author: Mo Hossny
Author-email: m.hossny@research.deakin.edu.au
License: UNKNOWN
Platform: UNKNOWN
Classifier: Development Status :: 4 - Beta
Classifier: Intended Audience :: Developers
Classifier: Topic :: Software Development :: Build Tools
Classifier: Programming Language :: Python :: 3.6
Classifier: Programming Language :: Python :: 3.7
Classifier: Programming Language :: Python :: 3.8
Classifier: License :: OSI Approved :: MIT License
Classifier: Operating System :: OS Independent
Requires-Python: >=3.6
Requires-Dist: docutils (>=0.3)
Requires-Dist: argparse
Requires-Dist: numpy
